.flake8
.gitignore
LICENSE
README.md
setup.py
docs/Makefile
docs/changelog.rst
docs/conf.py
docs/contrib.rst
docs/extend.rst
docs/index.rst
docs/install.rst
docs/make.bat
docs/markdown.rst
docs/misc.rst
docs/sample.rst
docs/usage.rst
sphinx_argparse_nni.egg-info/PKG-INFO
sphinx_argparse_nni.egg-info/SOURCES.txt
sphinx_argparse_nni.egg-info/dependency_links.txt
sphinx_argparse_nni.egg-info/requires.txt
sphinx_argparse_nni.egg-info/top_level.txt
sphinxarg4nni/__init__.py
sphinxarg4nni/ext.py
sphinxarg4nni/markdown.py
sphinxarg4nni/parser.py
test/__init__.py
test/sample.py
test/sample2.py
test/test_parser.py