Metadata-Version: 2.1
Name: sphinx-argparse-nni
Version: 0.4.0
Summary: A sphinx extension that automatically documents argparse commands and options, tailored for NNI
Home-page: https://github.com/ultmaster/sphinx-argparse
Author: Ash Berlin-Taylor, Yuge Zhang
Author-email: ash_github@firemirror.com, scottyugochang@gmail.com
License: UNKNOWN
Platform: UNKNOWN
Classifier: Programming Language :: Python :: 3
Classifier: License :: OSI Approved :: MIT License
Classifier: Operating System :: OS Independent
Classifier: Framework :: Sphinx :: Extension
Requires-Python: >=3.6
License-File: LICENSE
